{
  "total_examples": 375,
  "examples_by_intent": {
    "saludo": 10,
    "preguntar_como_estas": 16,
    "despedida": 9,
    "buscar_producto": 72,
    "buscar_oferta": 47,
    "modificar_busqueda": 47,
    "afirmar": 19,
    "denegar": 18,
    "completar_pedido": 36,
    "agradecimiento": 5,
    "off_topic": 14,
    "out_of_scope": 5,
    "ambiguity_fallback": 8,
    "agradecer": 15,
    "responder_como_estoy": 10,
    "pedir_chiste": 10,
    "reirse_chiste": 10,
    "consultar_novedades": 24
  },
  "examples_by_source": {
    "hardcoded": 83,
    "template": 292
  },
  "entity_usage": {
    "producto": 123,
    "sentimiento": 70,
    "proveedor": 46,
    "comparador": 39,
    "dia": 32,
    "animal": 22,
    "dosis": 22,
    "cantidad_descuento": 18,
    "tiempo": 12,
    "categoria": 12,
    "cantidad_bonificacion": 12,
    "indicador_temporal": 8,
    "cantidad": 6,
    "fecha": 6,
    "estado": 1
  },
  "generation_summary": {
    "total_intents": 18,
    "avg_examples_per_intent": 20.833333333333332
  }
}